noisify/__init__.py
noisify/attribute_readers/__init__.py
noisify/attribute_readers/attribute_readers.py
noisify/attribute_readers/inspection_strategies.py
noisify/faults/__init__.py
noisify/faults/attribute_faults.py
noisify/faults/fault.py
noisify/faults/report_faults.py
noisify/faults/utilities.py
noisify/helpers/__init__.py
noisify/helpers/fallible.py
noisify/helpers/multi_dispatch.py
noisify/helpers/saved_init_statement.py
noisify/recipes/__init__.py
noisify/recipes/default_recipes.py
noisify/reporters/__init__.py
noisify/reporters/report.py
noisify/reporters/reporter.py
noisify/reporters/series.py
noisify/tests/__init__.py
noisify/tests/attributes/__init__.py
noisify/tests/attributes/test_attribute.py
noisify/tests/attributes/test_object_attribute_introspection.py
noisify/tests/ecosystem/__init__.py
noisify/tests/ecosystem/test_numpy.py
noisify/tests/ecosystem/test_pandas.py
noisify/tests/ecosystem/test_pillow.py
noisify/tests/faults/__init__.py
noisify/tests/faults/test_attribute_faults.py
noisify/tests/faults/test_faults.py
noisify/tests/faults/test_report_faults.py
noisify/tests/helpers/__init__.py
noisify/tests/helpers/test_fallible.py
noisify/tests/helpers/test_init_saving.py
noisify/tests/recipes/__init__.py
noisify/tests/recipes/test_human_error.py
noisify/tests/recipes/test_machine_error.py
noisify/tests/reporters/__init__.py
noisify/tests/reporters/test_reports.py
noisify/tests/reporters/test_series.py
noisify-1.0.dist-info/LICENSE.txt
noisify-1.0.dist-info/METADATA
noisify-1.0.dist-info/WHEEL
noisify-1.0.dist-info/top_level.txt
noisify-1.0.dist-info/RECORD
