Metadata-Version: 2.1
Name: noisify
Version: 1.0
Summary: Framework for creating synthetic data with realistic errors for refining data science pipelines.
Home-page: https://github.com/dstl/Noisify
Author: Declan Crew
Author-email: dcrew@dstl.gov.uk
License: MIT
Platform: UNKNOWN
